setup.py
alquimia/__init__.py
alquimia/model.py
alquimia/modelmeta.py
alquimia/models.py
alquimia/models_attrs.py
alquimia/models_attrs_reflect.py
alquimia/utils.py
alquimia.egg-info/PKG-INFO
alquimia.egg-info/SOURCES.txt
alquimia.egg-info/dependency_links.txt
alquimia.egg-info/requires.txt
alquimia.egg-info/top_level.txt
alquimia/schemas/models.json