Metadata-Version: 1.1
Name: alquimia
Version: 0.7.1
Summary: An API to work with JSON schemas in SQLAlchemy
Home-page: http://packages.python.org/alquimia
Author: Diogo Dutra
Author-email: dutradda@gmail.com
License: LGPLv3
Keywords: json sqlachemy sql orm database
Platform: UNKNOWN
Classifier: Programming Language :: Python :: 2.7
Classifier: Development Status :: 3 - Alpha
Classifier: Intended Audience :: Developers
Classifier: Topic :: Database :: Front-Ends
Classifier: Topic :: Software Development :: Libraries :: Python Modules
Classifier: License :: OSI Approved :: GNU Lesser General Public License v3 (LGPLv3)
